MANIFEST.in
README.md
ez_setup.py
setup.py
bacula_configuration.egg-info/PKG-INFO
bacula_configuration.egg-info/SOURCES.txt
bacula_configuration.egg-info/dependency_links.txt
bacula_configuration.egg-info/entry_points.txt
bacula_configuration.egg-info/not-zip-safe
bacula_configuration.egg-info/requires.txt
bacula_configuration.egg-info/top_level.txt
bacula_tools/__init__.py
bacula_tools/bacula_config.py
bacula_tools/bacula_director.py
bacula_tools/catalog.py
bacula_tools/client.py
bacula_tools/console.py
bacula_tools/counter.py
bacula_tools/device.py
bacula_tools/director.py
bacula_tools/fd.py
bacula_tools/fileset.py
bacula_tools/job.py
bacula_tools/messages.py
bacula_tools/parser_support.py
bacula_tools/pool.py
bacula_tools/schedule.py
bacula_tools/scripts.py
bacula_tools/sd.py
bacula_tools/storage.py
bacula_tools/util.py
bin/bacula_webconfig
bin/change_storage
bin/check_bacula_hosts
bin/cleanpurged
bin/generate_configuration
bin/import_configuration
bin/pool_stats
bin/prune_volumes