Metadata-Version: 1.1
Name: bacula-configuration
Version: 0.94
Summary: Bacula configuration management tool
Home-page: http://gallew.org/bacula_configuration
Author: Brian Gallew
Author-email: bacula_configuration@gallew.org
License: UNKNOWN
Platform: UNKNOWN
Classifier: Development Status :: 4 - Beta
Classifier: Environment :: Console
Classifier: Intended Audience :: System Administrators
Classifier: Operating System :: OS Independent
Classifier: Programming Language :: Python
Classifier: License :: OSI Approved :: GNU General Public License (GPL)
Classifier: Topic :: Utilities
